odoo/addons/subbeticaecologica/__init__.py
odoo/addons/subbeticaecologica/__manifest__.py
odoo/addons/subbeticaecologica/i18n/es.po
odoo/addons/subbeticaecologica/report/__init__.py
odoo/addons/subbeticaecologica/report/sale_report.py
odoo/addons/subbeticaecologica/templates/portal_templates.xml
odoo12_addon_subbeticaecologica-12.0.0.0.2.dist-info/METADATA
odoo12_addon_subbeticaecologica-12.0.0.0.2.dist-info/WHEEL
odoo12_addon_subbeticaecologica-12.0.0.0.2.dist-info/top_level.txt
odoo12_addon_subbeticaecologica-12.0.0.0.2.dist-info/RECORD
